tachyon_engine-0.1.0.dist-info/METADATA
tachyon_engine-0.1.0.dist-info/WHEEL
tachyon_engine-0.1.0.dist-info/licenses/LICENSE
tachyon_engine/__init__.py
tachyon_engine/_internal.abi3.so
tachyon_engine-0.1.0.dist-info/RECORD
